LICENSE
MANIFEST.in
README
VERSION
setup.py
google/__init__.py
google/appengine/__init__.py
google/appengine/api/__init__.py
google/appengine/api/api_base_pb.py
google/appengine/api/apiproxy_rpc.py
google/appengine/api/apiproxy_stub.py
google/appengine/api/apiproxy_stub_map.py
google/appengine/api/app_logging.py
google/appengine/api/appinfo.py
google/appengine/api/appinfo_errors.py
google/appengine/api/appinfo_includes.py
google/appengine/api/backendinfo.py
google/appengine/api/conf.py
google/appengine/api/croninfo.py
google/appengine/api/datastore.py
google/appengine/api/datastore_admin.py
google/appengine/api/datastore_entities.py
google/appengine/api/datastore_errors.py
google/appengine/api/datastore_file_stub.py
google/appengine/api/datastore_types.py
google/appengine/api/dosinfo.py
google/appengine/api/lib_config.py
google/appengine/api/mail.py
google/appengine/api/mail_errors.py
google/appengine/api/mail_service_pb.py
google/appengine/api/mail_stub.py
google/appengine/api/queueinfo.py
google/appengine/api/quota.py
google/appengine/api/rdbms.py
google/appengine/api/rdbms_mysqldb.py
google/appengine/api/rdbms_sqlite.py
google/appengine/api/urlfetch.py
google/appengine/api/urlfetch_errors.py
google/appengine/api/urlfetch_service_pb.py
google/appengine/api/urlfetch_stub.py
google/appengine/api/user_service_pb.py
google/appengine/api/user_service_stub.py
google/appengine/api/users.py
google/appengine/api/validation.py
google/appengine/api/yaml_builder.py
google/appengine/api/yaml_errors.py
google/appengine/api/yaml_listener.py
google/appengine/api/yaml_object.py
google/appengine/api/app_identity/__init__.py
google/appengine/api/app_identity/app_identity.py
google/appengine/api/app_identity/app_identity_service_pb.py
google/appengine/api/app_identity/app_identity_stub.py
google/appengine/api/backends/__init__.py
google/appengine/api/backends/backends.py
google/appengine/api/blobstore/__init__.py
google/appengine/api/blobstore/blobstore.py
google_appengine.egg-info/PKG-INFO
google_appengine.egg-info/SOURCES.txt
google_appengine.egg-info/dependency_links.txt
google_appengine.egg-info/requires.txt
google_appengine.egg-info/top_level.txt
