Metadata-Version: 1.0
Name: google-appengine
Version: 1.5.1
Summary: Google AppEngine (unofficial easy-installable version of AppEngine SDK)
Home-page: https://github.com/worrp/gae-sdk
Author: Google
Author-email: UNKNOWN
License: Apache
Download-URL: http://pypi.python.org/packages/source/g/googleappengine/googleappengine-1.5.1.tar.gz
Platform: UNKNOWN
Classifier: Development Status :: 1 - Planning
Classifier: Intended Audience :: Developers
Classifier: License :: OSI Approved :: BSD License
Classifier: Programming Language :: Python
Classifier: Environment :: Web Environment
